{
  "mending-touch": {
    "id": "mending-touch",
    "name": "Mending Touch",
    "source": { "type": "magic", "college": "earthly", "school": "life", "focus": "healing", "requiredLevel": 1 },
    "apCost": 1,
    "componentCost": [{ "type": "LS", "amount": 1 }],
    "range": "touch",
    "target": "ally",
    "healing": { "dice": "2D10", "target": "hp" },
    "duration": "instant",
    "description": "Press your hands against wounded flesh and let vital energy flow. Target heals 2D10 HP.",
    "isPassive": false, "isRitual": false, "isSustained": false
  },
  "purge-ailment": {
    "id": "purge-ailment",
    "name": "Purge Ailment",
    "source": { "type": "magic", "college": "earthly", "school": "life", "focus": "healing", "requiredLevel": 1 },
    "apCost": 2,
    "componentCost": [{ "type": "LS", "amount": 1 }],
    "range": "touch",
    "target": "ally",
    "duration": "instant",
    "effects": { "removesConditions": ["poisoned", "burned", "minor disease"] },
    "description": "Draw sickness from the body. Remove one of: Poisoned, Burned (1 stack), or minor disease.",
    "isPassive": false, "isRitual": false, "isSustained": false
  },
  "vital-surge": {
    "id": "vital-surge",
    "name": "Vital Surge",
    "source": { "type": "magic", "college": "earthly", "school": "life", "focus": "healing", "requiredLevel": 1 },
    "apCost": 2,
    "componentCost": [{ "type": "LS", "amount": 2 }],
    "range": "touch",
    "target": "ally",
    "duration": "instant",
    "effects": { "special": ["Target regains 2D10 ST"] },
    "description": "Flood an ally's system with raw life energy. Their body remembers the strength it had forgotten. Target regains 2D10 ST.",
    "isPassive": false, "isRitual": false, "isSustained": false
  },
  "restoration": {
    "id": "restoration",
    "name": "Restoration",
    "source": { "type": "magic", "college": "earthly", "school": "life", "focus": "healing", "requiredLevel": 2 },
    "apCost": 3,
    "componentCost": [{ "type": "LS", "amount": 3 }],
    "staminaCost": 5,
    "range": "touch",
    "target": "ally",
    "healing": { "dice": "4D10", "target": "hp" },
    "duration": "instant",
    "effects": { "removesConditions": ["bleeding", "shocked", "broken bone"] },
    "description": "Pour sustained healing energy into a grievously wounded ally. Target heals 4D10 HP. Remove one: Bleeding, Shocked, or Broken Bone.",
    "isPassive": false, "isRitual": false, "isSustained": false
  },
  "life-link": {
    "id": "life-link",
    "name": "Life Link",
    "source": { "type": "magic", "college": "earthly", "school": "life", "focus": "healing", "requiredLevel": 2 },
    "apCost": 2,
    "componentCost": [{ "type": "LS", "amount": 2 }],
    "range": "30 ft",
    "target": "ally",
    "duration": "10 minutes",
    "effects": { "special": ["Link with target within 30 ft.", "You may take damage dealt to them"] },
    "description": "Bind your vitality to another's. When they suffer, you can choose to bear their wounds instead.",
    "isPassive": false, "isRitual": false, "isSustained": false
  },
  "mass-mending": {
    "id": "mass-mending",
    "name": "Mass Mending",
    "source": { "type": "magic", "college": "earthly", "school": "life", "focus": "healing", "requiredLevel": 3 },
    "apCost": 4,
    "componentCost": [{ "type": "LS", "amount": 4 }],
    "staminaCost": 10,
    "range": "self",
    "target": "area",
    "areaOfEffect": { "shape": "radius", "size": "20 ft" },
    "healing": { "dice": "3D10", "target": "hp" },
    "duration": "instant",
    "description": "Release a wave of healing energy that washes over all nearby allies. All allies within 20 ft. heal 3D10 HP.",
    "isPassive": false, "isRitual": false, "isSustained": false
  },
  "cleansing-light-life": {
    "id": "cleansing-light-life",
    "name": "Cleansing Light",
    "source": { "type": "magic", "college": "earthly", "school": "life", "focus": "healing", "requiredLevel": 3 },
    "apCost": 4,
    "componentCost": [{ "type": "LS", "amount": 5 }],
    "staminaCost": 10,
    "range": "touch",
    "target": "ally",
    "healing": { "dice": "5D10", "target": "hp" },
    "duration": "instant",
    "effects": { "special": ["Remove up to two conditions"] },
    "description": "Channel purifying life force through a target, burning away corruption and mending flesh simultaneously.",
    "isPassive": false, "isRitual": false, "isSustained": false
  },
  "breath-of-life": {
    "id": "breath-of-life",
    "name": "Breath of Life",
    "source": { "type": "magic", "college": "earthly", "school": "life", "focus": "healing", "requiredLevel": 4 },
    "apCost": 5,
    "componentCost": [{ "type": "LS", "amount": 8 }],
    "staminaCost": 20,
    "range": "touch",
    "target": "ally",
    "healing": { "dice": "8D10", "target": "hp" },
    "duration": "instant",
    "effects": { "special": ["Dying target stabilizes at 1 HP OR target heals 8D10 HP and removes all conditions", "Once per day"] },
    "description": "Call a dying soul back from the threshold. This is not resurrection - the target must still cling to life.",
    "isPassive": false, "isRitual": false, "isSustained": false
  },

  "enhance-physique": {
    "id": "enhance-physique",
    "name": "Enhance Physique",
    "source": { "type": "magic", "college": "earthly", "school": "life", "focus": "growth", "requiredLevel": 1 },
    "apCost": 1,
    "componentCost": [{ "type": "LS", "amount": 1 }],
    "range": "touch",
    "target": "ally",
    "duration": "10 minutes",
    "effects": { "statModifiers": [{ "stat": "MIT", "amount": 1 }, { "stat": "SPD", "amount": 1 }] },
    "description": "Flood a target's muscles with vital energy. They feel stronger, faster, more alive. Target gains +1 to MIT and SPD modifiers for 10 minutes.",
    "isPassive": false, "isRitual": false, "isSustained": false
  },
  "quicken-recovery": {
    "id": "quicken-recovery",
    "name": "Quicken Recovery",
    "source": { "type": "magic", "college": "earthly", "school": "life", "focus": "growth", "requiredLevel": 1 },
    "apCost": 2,
    "componentCost": [{ "type": "LS", "amount": 2 }],
    "range": "touch",
    "target": "ally",
    "healing": { "dice": "1D8", "target": "hp" },
    "duration": "3 rounds",
    "effects": { "special": ["Target heals 1D8 HP at start of each turn for 3 rounds"] },
    "description": "Accelerate the body's natural healing processes. Wounds that would take days begin knitting within minutes.",
    "isPassive": false, "isRitual": false, "isSustained": false
  },
  "bolster-vitality": {
    "id": "bolster-vitality",
    "name": "Bolster Vitality",
    "source": { "type": "magic", "college": "earthly", "school": "life", "focus": "growth", "requiredLevel": 1 },
    "apCost": 1,
    "componentCost": [{ "type": "LS", "amount": 1 }],
    "range": "touch",
    "target": "ally",
    "duration": "1 hour",
    "effects": { "temporaryHp": { "amount": 15, "duration": "1 hour" } },
    "description": "Infuse a target with surplus life energy, creating a buffer against incoming harm. Target gains 15 temporary HP.",
    "isPassive": false, "isRitual": false, "isSustained": false
  },
  "surge-of-strength": {
    "id": "surge-of-strength",
    "name": "Surge of Strength",
    "source": { "type": "magic", "college": "earthly", "school": "life", "focus": "growth", "requiredLevel": 2 },
    "apCost": 2,
    "componentCost": [{ "type": "LS", "amount": 3 }],
    "staminaCost": 5,
    "range": "touch",
    "target": "ally",
    "duration": "3 rounds",
    "effects": { "statModifiers": [{ "stat": "MIT", "amount": 3 }], "diceModifiers": [{ "amount": 1, "applies": "MIT checks" }], "special": ["+1D6 melee damage", "Costs 10 ST after effect ends"] },
    "description": "Push a target's physical capabilities far beyond normal limits. Muscles bulge, veins stand prominent.",
    "isPassive": false, "isRitual": false, "isSustained": false
  },
  "accelerated-reflexes": {
    "id": "accelerated-reflexes",
    "name": "Accelerated Reflexes",
    "source": { "type": "magic", "college": "earthly", "school": "life", "focus": "growth", "requiredLevel": 2 },
    "apCost": 2,
    "componentCost": [{ "type": "LS", "amount": 3 }],
    "staminaCost": 5,
    "range": "touch",
    "target": "ally",
    "duration": "3 rounds",
    "effects": { "diceModifiers": [{ "amount": 2, "applies": "defense" }, { "amount": 1, "applies": "SPD checks" }] },
    "description": "Quicken a target's nervous system until they perceive the world in slow motion.",
    "isPassive": false, "isRitual": false, "isSustained": false
  },
  "primal-vigor": {
    "id": "primal-vigor",
    "name": "Primal Vigor",
    "source": { "type": "magic", "college": "earthly", "school": "life", "focus": "growth", "requiredLevel": 3 },
    "apCost": 4,
    "componentCost": [{ "type": "LS", "amount": 5 }],
    "staminaCost": 10,
    "range": "touch",
    "target": "ally",
    "duration": "5 rounds",
    "effects": { "statModifiers": [{ "stat": "all physical", "amount": 2 }], "diceModifiers": [{ "amount": 1, "applies": "physical rolls" }], "temporaryHp": { "amount": 20 }, "movement": { "amount": 10 }, "special": ["Fatigued after effect ends"] },
    "description": "Unleash the full potential of a target's body. They become a creature of pure physical prowess.",
    "isPassive": false, "isRitual": false, "isSustained": false
  },
  "adaptive-form": {
    "id": "adaptive-form",
    "name": "Adaptive Form",
    "source": { "type": "magic", "college": "earthly", "school": "life", "focus": "growth", "requiredLevel": 3 },
    "apCost": 3,
    "componentCost": [{ "type": "LS", "amount": 4 }],
    "staminaCost": 5,
    "range": "touch",
    "target": "ally",
    "duration": "1 hour",
    "effects": { "grants": ["Resistance to one damage type (halved)", "Immunity to one environmental hazard"] },
    "description": "Trigger rapid biological adaptation, allowing the body to respond to environmental threats.",
    "isPassive": false, "isRitual": false, "isSustained": false
  },
  "apex-predator": {
    "id": "apex-predator",
    "name": "Apex Predator",
    "source": { "type": "magic", "college": "earthly", "school": "life", "focus": "growth", "requiredLevel": 4 },
    "apCost": 5,
    "componentCost": [{ "type": "LS", "amount": 8 }],
    "staminaCost": 15,
    "range": "touch",
    "target": "ally",
    "duration": "3 rounds",
    "effects": { "statModifiers": [{ "stat": "all physical", "amount": 4 }], "diceModifiers": [{ "amount": 2, "applies": "all physical rolls" }], "temporaryHp": { "amount": 50 }, "movement": { "amount": 20 }, "ap": { "amount": 1 }, "special": ["+2D10 damage", "Heavy cost after effect ends"] },
    "description": "Transform a willing target into the ultimate expression of physical perfection.",
    "isPassive": false, "isRitual": false, "isSustained": false
  },

  "beast-speech": {
    "id": "beast-speech",
    "name": "Beast Speech",
    "source": { "type": "magic", "college": "earthly", "school": "life", "focus": "beasts", "requiredLevel": 1 },
    "apCost": 1,
    "componentCost": [{ "type": "LS", "amount": 1 }],
    "range": "self",
    "target": "self",
    "duration": "1 hour",
    "effects": { "grants": ["Communicate with animals for 1 hour"], "special": ["Animals not automatically friendly", "Complex concepts difficult"] },
    "description": "Open your mind to the language of animals. You understand their communications and can make yourself understood.",
    "isPassive": false, "isRitual": false, "isSustained": false
  },
  "summon-companion": {
    "id": "summon-companion",
    "name": "Summon Companion",
    "source": { "type": "magic", "college": "earthly", "school": "life", "focus": "beasts", "requiredLevel": 1 },
    "apCost": 2,
    "componentCost": [{ "type": "LS", "amount": 2 }],
    "range": "30 ft",
    "target": "special",
    "duration": "10 minutes",
    "summon": {
      "creatureId": "small-beast",
      "creature": { "id": "small-beast", "name": "Small Beast", "hp": 20, "stamina": 15, "attacks": [{ "name": "Bite/Claw/Talon", "type": "physical", "damage": "2D6", "apCost": 2 }], "passives": ["Pack Tactics: +1 D20 when ally within 5 ft. of target"] }
    },
    "description": "Call out to the local wildlife and request aid. A creature answers - not a servant, but a partner. Flees below 25% HP unless defending you.",
    "isPassive": false, "isRitual": false, "isSustained": false
  },
  "predators-senses": {
    "id": "predators-senses",
    "name": "Predator's Senses",
    "source": { "type": "magic", "college": "earthly", "school": "life", "focus": "beasts", "requiredLevel": 1 },
    "apCost": 2,
    "componentCost": [{ "type": "LS", "amount": 1 }],
    "range": "self",
    "target": "self",
    "duration": "1 hour",
    "effects": { "grants": ["Darkvision 60 ft.", "Detect invisible within 10 ft."], "diceModifiers": [{ "amount": 2, "applies": "perception" }], "special": ["Tracking advantage"] },
    "description": "Borrow the keen senses of a hunting animal. Your eyes sharpen, ears tune to subtle sounds.",
    "isPassive": false, "isRitual": false, "isSustained": false,
    "notes": "You get ears!"
  },
  "call-the-pack": {
    "id": "call-the-pack",
    "name": "Call the Pack",
    "source": { "type": "magic", "college": "earthly", "school": "life", "focus": "beasts", "requiredLevel": 2 },
    "apCost": 3,
    "componentCost": [{ "type": "LS", "amount": 3 }],
    "staminaCost": 5,
    "range": "30 ft",
    "target": "special",
    "duration": "5 minutes",
    "effects": { "special": ["Summon 3 Small Beasts", "Share initiative, coordinate attacks"] },
    "description": "Your call reaches further, and more creatures answer. A small group of beasts arrives.",
    "isPassive": false, "isRitual": false, "isSustained": false
  },
  "aspect-of-the-beast": {
    "id": "aspect-of-the-beast",
    "name": "Aspect of the Beast",
    "source": { "type": "magic", "college": "earthly", "school": "life", "focus": "beasts", "requiredLevel": 2 },
    "apCost": 2,
    "componentCost": [{ "type": "LS", "amount": 2 }],
    "staminaCost": 5,
    "range": "self",
    "target": "self",
    "duration": "10 minutes",
    "effects": { "special": ["Choose: Wolf (+10 ft., pack tactics), Bear (+2 GRT, +10 temp HP), Hawk (+20 ft. range, +2 D20 perception), Cat (+2 D20 stealth, no fall damage)"] },
    "description": "Channel the essence of an animal through your own body. Your features shift subtly as you take on bestial traits.",
    "isPassive": false, "isRitual": false, "isSustained": false,
    "notes": "So many animals!"
  },
  "summon-greater-beast": {
    "id": "summon-greater-beast",
    "name": "Summon Greater Beast",
    "source": { "type": "magic", "college": "earthly", "school": "life", "focus": "beasts", "requiredLevel": 3 },
    "apCost": 3,
    "componentCost": [{ "type": "LS", "amount": 5 }],
    "staminaCost": 10,
    "range": "30 ft",
    "target": "special",
    "duration": "5 rounds",
    "summon": {
      "creatureId": "greater-beast",
      "creature": { "id": "greater-beast", "name": "Greater Beast", "hp": 60, "stamina": 30, "attacks": [{ "name": "Savage Strike", "type": "physical", "damage": "4D8", "statModifier": "MIT", "apCost": 3 }, { "name": "Pounce", "type": "physical", "damage": "3D8", "statModifier": "MIT", "apCost": 4, "special": "If moved 20+ ft., target makes SPD+GRT (Diff 35) or knocked prone" }], "passives": ["Intimidating Presence: Enemies within 10 ft. suffer -1 D20 on COR checks"] }
    },
    "description": "Call upon a more powerful creature - a true predator of the wild.",
    "isPassive": false, "isRitual": false, "isSustained": false
  },
  "feral-mind": {
    "id": "feral-mind",
    "name": "Feral Mind",
    "source": { "type": "magic", "college": "earthly", "school": "life", "focus": "beasts", "requiredLevel": 3 },
    "apCost": 3,
    "componentCost": [{ "type": "LS", "amount": 4 }],
    "staminaCost": 10,
    "range": "self",
    "target": "self",
    "duration": "3 rounds",
    "effects": { "diceModifiers": [{ "amount": 2, "applies": "attack and defense" }], "statModifiers": [{ "stat": "all physical", "amount": 1 }], "grants": ["Immune to Charmed/Terrified"], "special": ["Must attack nearest enemy unless DET check (Diff 30)"] },
    "description": "Temporarily surrender your civilized thoughts to pure animal instinct.",
    "isPassive": false, "isRitual": false, "isSustained": false
  },
  "alphas-command": {
    "id": "alphas-command",
    "name": "Alpha's Command",
    "source": { "type": "magic", "college": "earthly", "school": "life", "focus": "beasts", "requiredLevel": 4 },
    "apCost": 5,
    "componentCost": [{ "type": "LS", "amount": 8 }],
    "staminaCost": 15,
    "range": "self",
    "target": "area",
    "areaOfEffect": { "shape": "radius", "size": "60 ft" },
    "duration": "1 hour",
    "effects": { "diceModifiers": [{ "amount": 2, "applies": "summoned beast rolls" }], "temporaryHp": { "amount": 20, "target": "summoned beasts" }, "special": ["Non-magical beasts in 60 ft. make DET check (Diff 50) or become friendly for 1 hour"] },
    "description": "You become the undisputed master of all beasts in the area.",
    "isPassive": false, "isRitual": false, "isSustained": false
  },

  "grasping-roots": {
    "id": "grasping-roots",
    "name": "Grasping Roots",
    "source": { "type": "magic", "college": "earthly", "school": "life", "focus": "plants", "requiredLevel": 1 },
    "apCost": 2,
    "componentCost": [{ "type": "LS", "amount": 1 }],
    "range": "30 ft",
    "target": "enemy",
    "duration": "3 rounds",
    "effects": { "appliesConditions": [{ "condition": "restrained", "save": { "stat": "SPD + MIT", "difficulty": 30 }, "duration": "3 rounds" }], "special": ["Repeat save each turn"] },
    "description": "Command roots and vines to erupt from the ground and seize a target. The plants grip with surprising strength.",
    "isPassive": false, "isRitual": false, "isSustained": false
  },
  "thorn-shot": {
    "id": "thorn-shot",
    "name": "Thorn Shot",
    "source": { "type": "magic", "college": "earthly", "school": "life", "focus": "plants", "requiredLevel": 1 },
    "apCost": 1,
    "componentCost": [{ "type": "LS", "amount": 1 }],
    "range": "40 ft",
    "target": "enemy",
    "damage": { "dice": "2D8", "statModifier": "NAT", "type": "physical" },
    "duration": "instant",
    "effects": { "appliesConditions": [{ "condition": "bleeding", "save": { "stat": "GRT", "difficulty": 25 } }] },
    "description": "Harden a seed or thorn with vital energy and launch it at high velocity, leaving a bleeding wound.",
    "isPassive": false, "isRitual": false, "isSustained": false
  },
  "verdant-sense": {
    "id": "verdant-sense",
    "name": "Verdant Sense",
    "source": { "type": "magic", "college": "earthly", "school": "life", "focus": "plants", "requiredLevel": 1 },
    "apCost": 2,
    "componentCost": [{ "type": "LS", "amount": 1 }],
    "range": "self",
    "target": "self",
    "duration": "1 hour",
    "effects": { "grants": ["Sense creatures within 60 ft. on natural ground", "Cannot be surprised"], "diceModifiers": [{ "amount": 2, "applies": "perception" }] },
    "description": "Attune yourself to the plants around you. They whisper of movement and disturbance.",
    "isPassive": false, "isRitual": false, "isSustained": false,
    "notes": "One with nature."
  },
  "wall-of-thorns": {
    "id": "wall-of-thorns",
    "name": "Wall of Thorns",
    "source": { "type": "magic", "college": "earthly", "school": "life", "focus": "plants", "requiredLevel": 2 },
    "apCost": 3,
    "componentCost": [{ "type": "LS", "amount": 3 }],
    "staminaCost": 5,
    "range": "30 ft",
    "target": "area",
    "damage": { "dice": "3D10", "type": "physical" },
    "duration": "5 rounds",
    "effects": { "appliesConditions": [{ "condition": "bleeding" }], "special": ["30 ft. long, 10 ft. high wall", "Provides full cover", "3D10 damage + Bleeding to pass through"] },
    "description": "Command a barrier of dense, thorn-covered vegetation to erupt from the ground.",
    "isPassive": false, "isRitual": false, "isSustained": false
  },
  "barkskin": {
    "id": "barkskin",
    "name": "Barkskin",
    "source": { "type": "magic", "college": "earthly", "school": "life", "focus": "plants", "requiredLevel": 2 },
    "apCost": 2,
    "componentCost": [{ "type": "LS", "amount": 2 }],
    "range": "touch",
    "target": "ally",
    "duration": "10 minutes",
    "effects": { "diceModifiers": [{ "amount": 2, "applies": "defense vs physical" }], "statModifiers": [{ "stat": "SPD", "amount": -1 }] },
    "description": "Call upon the resilience of ancient trees to harden a target's skin to woody texture.",
    "isPassive": false, "isRitual": false, "isSustained": false
  },
  "strangling-vines": {
    "id": "strangling-vines",
    "name": "Strangling Vines",
    "source": { "type": "magic", "college": "earthly", "school": "life", "focus": "plants", "requiredLevel": 3 },
    "apCost": 3,
    "componentCost": [{ "type": "LS", "amount": 4 }],
    "staminaCost": 10,
    "range": "30 ft",
    "target": "enemy",
    "damage": { "dice": "3D8", "statModifier": "NAT", "type": "physical" },
    "duration": "3 rounds",
    "effects": { "appliesConditions": [{ "condition": "restrained" }], "special": ["2D8 damage each turn", "MIT + GRT check (Diff 40) to escape"] },
    "description": "Command aggressive vegetation to assault a target. Vines wrap around limbs and throat.",
    "isPassive": false, "isRitual": false, "isSustained": false
  },
  "summon-treant-sapling": {
    "id": "summon-treant-sapling",
    "name": "Summon Treant Sapling",
    "source": { "type": "magic", "college": "earthly", "school": "life", "focus": "plants", "requiredLevel": 3 },
    "apCost": 4,
    "componentCost": [{ "type": "LS", "amount": 5 }],
    "staminaCost": 10,
    "range": "30 ft",
    "target": "special",
    "duration": "5 rounds",
    "summon": {
      "creatureId": "treant-sapling",
      "creature": { "id": "treant-sapling", "name": "Treant Sapling", "hp": 50, "stamina": 20, "attacks": [{ "name": "Branch Slam", "type": "physical", "damage": "3D10", "apCost": 3 }, { "name": "Entangling Roots", "type": "special", "apCost": 2, "special": "Target within 20 ft. makes SPD check (Diff 35) or Restrained until end of next turn" }], "passives": ["Rooted Defense: Cannot move, but gains +2 D20 on defensive rolls"] }
    },
    "description": "Call upon the spirit of the forest to animate a young tree. It pulls itself from the earth to defend you. Requires tree within 30 ft.",
    "isPassive": false, "isRitual": false, "isSustained": false
  },
  "summon-thornweaver": {
    "id": "summon-thornweaver",
    "name": "Summon Thornweaver",
    "source": { "type": "magic", "college": "earthly", "school": "life", "focus": "plants", "requiredLevel": 3 },
    "apCost": 3,
    "componentCost": [{ "type": "LS", "amount": 4 }],
    "staminaCost": 10,
    "range": "30 ft",
    "target": "special",
    "duration": "5 rounds",
    "summon": {
      "creatureId": "thornweaver",
      "creature": { "id": "thornweaver", "name": "Thornweaver", "hp": 40, "stamina": 25, "attacks": [{ "name": "Thorn Lash", "type": "physical", "damage": "2D10", "statModifier": "NAT", "apCost": 2, "special": "15 ft. reach. GRT check (Diff 30) or Bleeding" }, { "name": "Thorn Spray", "type": "physical", "damage": "2D8", "apCost": 3, "special": "All enemies in 15 ft. cone. GRT check (Diff 25) or Bleeding" }] }
    },
    "description": "Awaken a mass of thorny vines into a semi-sentient guardian that lashes at your enemies. Requires natural ground.",
    "isPassive": false, "isRitual": false, "isSustained": false
  }
}